Workbook

Sheet Index
A1: Workbook Index
A3: Sheet | B3: Rows | C3: Description | D3: Depends on
A4: Products | B4: 40 | C4: Product catalog: cost, price, margin | D4: (none -- source table)
A5: Regions | B5: 8 | C5: Regional tax/discount rules | D5: (none -- source table)
A6: Customers | B6: 120 | C6: Customer master data, one region each | D6: Regions (RegionID)
A7: Sales | B7: 400 | C7: Transactions: full pricing/tax/discount chain | D7: Products, Customers, Regions
A8: Summary | B8: - | C8: Rollups by category/region + one INDIRECT example | D8: Sales, Products, Regions

Sheet Products
A1: ProductID | B1: ProductName | C1: Category | D1: UnitCost | E1: UnitPrice | F1: Margin
A2: P001 | B2: Pro Blender | C2: Office Supplies | D2: 65 | E2: 89.87 | F2: =(E2-D2)/E2 -> 0.27673306
A3: P002 | B3: Pro Mug | C3: Apparel | D3: 26.3 | E3: 43.42 | F3: =(E3-D3)/E3 -> 0.39428835
A4: P003 | B4: Compact Monitor | C4: Home & Kitchen | D4: 62 | E4: 112.96 | F4: =(E4-D4)/E4 -> 0.45113314
A5: P004 | B5: Basic Keyboard | C5: Apparel | D5: 107.78 | E5: 180.72 | F5: =(E5-D5)/E5 -> 0.40360779
A6: P005 | B6: Deluxe Headphones | C6: Electronics | D6: 190.91 | E6: 267.59 | F6: =(E6-D6)/E6 -> 0.28655779
A7: P006 | B7: Smart Speaker | C7: Office Supplies | D7: 43.09 | E7: 93.05 | F7: =(E7-D7)/E7 -> 0.53691564
A8: P007 | B8: Portable Monitor | C8: Electronics | D8: 98.08 | E8: 156.05 | F8: =(E8-D8)/E8 -> 0.3714835
A9: P008 | B9: Portable Tent | C9: Office Supplies | D9: 202.75 | E9: 393.99 | F9: =(E9-D9)/E9 -> 0.48539303
A10: P009 | B10: Pro Lantern | C10: Outdoor | D10: 24.31 | E10: 37.16 | F10: =(E10-D10)/E10 -> 0.34580194
A11: P010 | B11: Portable Tent | C11: Home & Kitchen | D11: 177.62 | E11: 229.76 | F11: =(E11-D11)/E11 -> 0.22693245
A12: P011 | B12: Basic Headphones | C12: Office Supplies | D12: 246.38 | E12: 508.17 | F12: =(E12-D12)/E12 -> 0.51516225
A13: P012 | B13: Pro Jacket | C13: Office Supplies | D13: 116.09 | E13: 237.1 | F13: =(E13-D13)/E13 -> 0.51037537
... A41: P040 | B41: Ultra Keyboard | C41: Apparel | D41: 146.17 | E41: 216.46 | F41: =(E41-D41)/E41 -> 0.32472512

Sheet Regions
A1: RegionID | B1: RegionName | C1: TaxRate | D1: DiscountRate | E1: DiscountThreshold
A2: R01 | B2: Northeast | C2: 0.0825 | D2: 0.05 | E2: 10
A3: R02 | B3: Southeast | C3: 0.07 | D3: 0.04 | E3: 12
A4: R03 | B4: Midwest | C4: 0.0625 | D4: 0.03 | E4: 15
A5: R04 | B5: Southwest | C5: 0.08 | D5: 0.05 | E5: 10
A6: R05 | B6: Pacific | C6: 0.0925 | D6: 0.06 | E6: 8
A7: R06 | B7: Mountain | C7: 0.06 | D7: 0.04 | E7: 12
A8: R07 | B8: Atlantic Canada | C8: 0.15 | D8: 0.05 | E8: 10
A9: R08 | B9: Prairies | C9: 0.12 | D9: 0.04 | E9: 12

Sheet Customers
A1: CustomerID | B1: CustomerName | C1: RegionID | D1: Segment | E1: CreditLimit
A2: C0001 | B2: Ironwood Distribution | C2: R04 | D2: Retail | E2: 6700
A3: C0002 | B3: Golden Gate Holdings | C3: R07 | D3: Wholesale | E3: 24400
A4: C0003 | B4: Summit Traders | C4: R02 | D4: Retail | E4: 21300
A5: C0004 | B5: Redwood Supply Co. | C5: R04 | D5: Retail | E5: 11100
A6: C0005 | B6: Ironwood Logistics | C6: R07 | D6: Retail | E6: 15400
A7: C0006 | B7: Cedar Grove Supply Co. | C7: R08 | D7: Online | E7: 6700
A8: C0007 | B8: Maple Leaf Market | C8: R01 | D8: Retail | E8: 46500
A9: C0008 | B9: Cedar Grove Logistics | C9: R07 | D9: Wholesale | E9: 25100
A10: C0009 | B10: Golden Gate Traders | C10: R03 | D10: Wholesale | E10: 2100
A11: C0010 | B11: Golden Gate Partners | C11: R08 | D11: Wholesale | E11: 22300
A12: C0011 | B12: Summit Market | C12: R08 | D12: Retail | E12: 11100
A13: C0012 | B13: Cedar Grove Traders | C13: R01 | D13: Online | E13: 17100
... A121: C0120 | B121: Blue Ridge Retail Group | C121: R02 | D121: Online | E121: 38700

Sheet Sales
A1: TransactionID | B1: Date | C1: ProductID | D1: CustomerID | E1: Quantity | F1: UnitPrice | G1: Category | H1: RegionID | I1: TaxRate | J1: DiscountRate | K1: DiscountThreshold | L1: Subtotal | M1: Discount | N1: TaxAmount | O1: Total
A2: T00001 | B2: 45974 | C2: P039 | D2: C0077 | E2: 26 | F2: =INDEX(Products!$E:$E,MATCH(C2,Products!$A:$A,0)) -> 125.31 | G2: =INDEX(Products!$C:$C,MATCH(C2,Products!$A:$A,0)) -> Home & Kitchen | H2: =INDEX(Customers!$C:$C,MATCH(D2,Customers!$A:$A,0)) -> R03 | I2: =INDEX(Regions!$C:$C,MATCH(H2,Regions!$A:$A,0)) -> 0.0625 | J2: =INDEX(Regions!$D:$D,MATCH(H2,Regions!$A:$A,0)) -> 0.03 | K2: =INDEX(Regions!$E:$E,MATCH(H2,Regions!$A:$A,0)) -> 15 | L2: =E2*F2 -> 3258.06 | M2: =IF(E2>=K2,L2*J2,0) -> 97.7418 | N2: =(L2-M2)*I2 -> 197.51989 | O2: =L2-M2+N2 -> 3357.8381
A3: T00002 | B3: 45852 | C3: P015 | D3: C0100 | E3: 17 | F3: =INDEX(Products!$E:$E,MATCH(C3,Products!$A:$A,0)) -> 459.72 | G3: =INDEX(Products!$C:$C,MATCH(C3,Products!$A:$A,0)) -> Office Supplies | H3: =INDEX(Customers!$C:$C,MATCH(D3,Customers!$A:$A,0)) -> R08 | I3: =INDEX(Regions!$C:$C,MATCH(H3,Regions!$A:$A,0)) -> 0.12 | J3: =INDEX(Regions!$D:$D,MATCH(H3,Regions!$A:$A,0)) -> 0.04 | K3: =INDEX(Regions!$E:$E,MATCH(H3,Regions!$A:$A,0)) -> 12 | L3: =E3*F3 -> 7815.24 | M3: =IF(E3>=K3,L3*J3,0) -> 312.6096 | N3: =(L3-M3)*I3 -> 900.31565 | O3: =L3-M3+N3 -> 8402.946
A4: T00003 | B4: 45810 | C4: P029 | D4: C0117 | E4: 15 | F4: =INDEX(Products!$E:$E,MATCH(C4,Products!$A:$A,0)) -> 338.07 | G4: =INDEX(Products!$C:$C,MATCH(C4,Products!$A:$A,0)) -> Office Supplies | H4: =INDEX(Customers!$C:$C,MATCH(D4,Customers!$A:$A,0)) -> R08 | I4: =INDEX(Regions!$C:$C,MATCH(H4,Regions!$A:$A,0)) -> 0.12 | J4: =INDEX(Regions!$D:$D,MATCH(H4,Regions!$A:$A,0)) -> 0.04 | K4: =INDEX(Regions!$E:$E,MATCH(H4,Regions!$A:$A,0)) -> 12 | L4: =E4*F4 -> 5071.05 | M4: =IF(E4>=K4,L4*J4,0) -> 202.842 | N4: =(L4-M4)*I4 -> 584.18496 | O4: =L4-M4+N4 -> 5452.393
A5: T00004 | B5: 45949 | C5: P038 | D5: C0055 | E5: 10 | F5: =INDEX(Products!$E:$E,MATCH(C5,Products!$A:$A,0)) -> 468.78 | G5: =INDEX(Products!$C:$C,MATCH(C5,Products!$A:$A,0)) -> Electronics | H5: =INDEX(Customers!$C:$C,MATCH(D5,Customers!$A:$A,0)) -> R06 | I5: =INDEX(Regions!$C:$C,MATCH(H5,Regions!$A:$A,0)) -> 0.06 | J5: =INDEX(Regions!$D:$D,MATCH(H5,Regions!$A:$A,0)) -> 0.04 | K5: =INDEX(Regions!$E:$E,MATCH(H5,Regions!$A:$A,0)) -> 12 | L5: =E5*F5 -> 4687.8 | M5: =IF(E5>=K5,L5*J5,0) -> 0 | N5: =(L5-M5)*I5 -> 281.268 | O5: =L5-M5+N5 -> 4969.068
A6: T00005 | B6: 45708 | C6: P040 | D6: C0008 | E6: 20 | F6: =INDEX(Products!$E:$E,MATCH(C6,Products!$A:$A,0)) -> 216.46 | G6: =INDEX(Products!$C:$C,MATCH(C6,Products!$A:$A,0)) -> Apparel | H6: =INDEX(Customers!$C:$C,MATCH(D6,Customers!$A:$A,0)) -> R07 | I6: =INDEX(Regions!$C:$C,MATCH(H6,Regions!$A:$A,0)) -> 0.15 | J6: =INDEX(Regions!$D:$D,MATCH(H6,Regions!$A:$A,0)) -> 0.05 | K6: =INDEX(Regions!$E:$E,MATCH(H6,Regions!$A:$A,0)) -> 10 | L6: =E6*F6 -> 4329.2 | M6: =IF(E6>=K6,L6*J6,0) -> 216.46 | N6: =(L6-M6)*I6 -> 616.911 | O6: =L6-M6+N6 -> 4729.651
A7: T00006 | B7: 45793 | C7: P014 | D7: C0081 | E7: 7 | F7: =INDEX(Products!$E:$E,MATCH(C7,Products!$A:$A,0)) -> 201.42 | G7: =INDEX(Products!$C:$C,MATCH(C7,Products!$A:$A,0)) -> Home & Kitchen | H7: =INDEX(Customers!$C:$C,MATCH(D7,Customers!$A:$A,0)) -> R06 | I7: =INDEX(Regions!$C:$C,MATCH(H7,Regions!$A:$A,0)) -> 0.06 | J7: =INDEX(Regions!$D:$D,MATCH(H7,Regions!$A:$A,0)) -> 0.04 | K7: =INDEX(Regions!$E:$E,MATCH(H7,Regions!$A:$A,0)) -> 12 | L7: =E7*F7 -> 1409.94 | M7: =IF(E7>=K7,L7*J7,0) -> 0 | N7: =(L7-M7)*I7 -> 84.5964 | O7: =L7-M7+N7 -> 1494.5364
A8: T00007 | B8: 45746 | C8: P006 | D8: C0021 | E8: 8 | F8: =INDEX(Products!$E:$E,MATCH(C8,Products!$A:$A,0)) -> 93.05 | G8: =INDEX(Products!$C:$C,MATCH(C8,Products!$A:$A,0)) -> Office Supplies | H8: =INDEX(Customers!$C:$C,MATCH(D8,Customers!$A:$A,0)) -> R08 | I8: =INDEX(Regions!$C:$C,MATCH(H8,Regions!$A:$A,0)) -> 0.12 | J8: =INDEX(Regions!$D:$D,MATCH(H8,Regions!$A:$A,0)) -> 0.04 | K8: =INDEX(Regions!$E:$E,MATCH(H8,Regions!$A:$A,0)) -> 12 | L8: =E8*F8 -> 744.4 | M8: =IF(E8>=K8,L8*J8,0) -> 0 | N8: =(L8-M8)*I8 -> 89.328 | O8: =L8-M8+N8 -> 833.728
A9: T00008 | B9: 45659 | C9: P036 | D9: C0010 | E9: 6 | F9: =INDEX(Products!$E:$E,MATCH(C9,Products!$A:$A,0)) -> 26.28 | G9: =INDEX(Products!$C:$C,MATCH(C9,Products!$A:$A,0)) -> Home & Kitchen | H9: =INDEX(Customers!$C:$C,MATCH(D9,Customers!$A:$A,0)) -> R08 | I9: =INDEX(Regions!$C:$C,MATCH(H9,Regions!$A:$A,0)) -> 0.12 | J9: =INDEX(Regions!$D:$D,MATCH(H9,Regions!$A:$A,0)) -> 0.04 | K9: =INDEX(Regions!$E:$E,MATCH(H9,Regions!$A:$A,0)) -> 12 | L9: =E9*F9 -> 157.68 | M9: =IF(E9>=K9,L9*J9,0) -> 0 | N9: =(L9-M9)*I9 -> 18.9216 | O9: =L9-M9+N9 -> 176.6016
A10: T00009 | B10: 45962 | C10: P027 | D10: C0058 | E10: 23 | F10: =INDEX(Products!$E:$E,MATCH(C10,Products!$A:$A,0)) -> 479.87 | G10: =INDEX(Products!$C:$C,MATCH(C10,Products!$A:$A,0)) -> Office Supplies | H10: =INDEX(Customers!$C:$C,MATCH(D10,Customers!$A:$A,0)) -> R04 | I10: =INDEX(Regions!$C:$C,MATCH(H10,Regions!$A:$A,0)) -> 0.08 | J10: =INDEX(Regions!$D:$D,MATCH(H10,Regions!$A:$A,0)) -> 0.05 | K10: =INDEX(Regions!$E:$E,MATCH(H10,Regions!$A:$A,0)) -> 10 | L10: =E10*F10 -> 11037.01 | M10: =IF(E10>=K10,L10*J10,0) -> 551.8505 | N10: =(L10-M10)*I10 -> 838.81276 | O10: =L10-M10+N10 -> 11323.972
A11: T00010 | B11: 45776 | C11: P031 | D11: C0038 | E11: 2 | F11: =INDEX(Products!$E:$E,MATCH(C11,Products!$A:$A,0)) -> 94.16 | G11: =INDEX(Products!$C:$C,MATCH(C11,Products!$A:$A,0)) -> Office Supplies | H11: =INDEX(Customers!$C:$C,MATCH(D11,Customers!$A:$A,0)) -> R07 | I11: =INDEX(Regions!$C:$C,MATCH(H11,Regions!$A:$A,0)) -> 0.15 | J11: =INDEX(Regions!$D:$D,MATCH(H11,Regions!$A:$A,0)) -> 0.05 | K11: =INDEX(Regions!$E:$E,MATCH(H11,Regions!$A:$A,0)) -> 10 | L11: =E11*F11 -> 188.32 | M11: =IF(E11>=K11,L11*J11,0) -> 0 | N11: =(L11-M11)*I11 -> 28.248 | O11: =L11-M11+N11 -> 216.568
A12: T00011 | B12: 46017 | C12: P019 | D12: C0091 | E12: 10 | F12: =INDEX(Products!$E:$E,MATCH(C12,Products!$A:$A,0)) -> 55.31 | G12: =INDEX(Products!$C:$C,MATCH(C12,Products!$A:$A,0)) -> Outdoor | H12: =INDEX(Customers!$C:$C,MATCH(D12,Customers!$A:$A,0)) -> R02 | I12: =INDEX(Regions!$C:$C,MATCH(H12,Regions!$A:$A,0)) -> 0.07 | J12: =INDEX(Regions!$D:$D,MATCH(H12,Regions!$A:$A,0)) -> 0.04 | K12: =INDEX(Regions!$E:$E,MATCH(H12,Regions!$A:$A,0)) -> 12 | L12: =E12*F12 -> 553.1 | M12: =IF(E12>=K12,L12*J12,0) -> 0 | N12: =(L12-M12)*I12 -> 38.717 | O12: =L12-M12+N12 -> 591.817
A13: T00012 | B13: 45777 | C13: P030 | D13: C0010 | E13: 22 | F13: =INDEX(Products!$E:$E,MATCH(C13,Products!$A:$A,0)) -> 169.14 | G13: =INDEX(Products!$C:$C,MATCH(C13,Products!$A:$A,0)) -> Office Supplies | H13: =INDEX(Customers!$C:$C,MATCH(D13,Customers!$A:$A,0)) -> R08 | I13: =INDEX(Regions!$C:$C,MATCH(H13,Regions!$A:$A,0)) -> 0.12 | J13: =INDEX(Regions!$D:$D,MATCH(H13,Regions!$A:$A,0)) -> 0.04 | K13: =INDEX(Regions!$E:$E,MATCH(H13,Regions!$A:$A,0)) -> 12 | L13: =E13*F13 -> 3721.08 | M13: =IF(E13>=K13,L13*J13,0) -> 148.8432 | N13: =(L13-M13)*I13 -> 428.66842 | O13: =L13-M13+N13 -> 4000.9052
... A401: T00400 | B401: 45731 | C401: P022 | D401: C0072 | E401: 12 | F401: =INDEX(Products!$E:$E,MATCH(C401,Products!$A:$A,0)) -> 59.51 | G401: =INDEX(Products!$C:$C,MATCH(C401,Products!$A:$A,0)) -> Electronics | H401: =INDEX(Customers!$C:$C,MATCH(D401,Customers!$A:$A,0)) -> R08 | I401: =INDEX(Regions!$C:$C,MATCH(H401,Regions!$A:$A,0)) -> 0.12 | J401: =INDEX(Regions!$D:$D,MATCH(H401,Regions!$A:$A,0)) -> 0.04 | K401: =INDEX(Regions!$E:$E,MATCH(H401,Regions!$A:$A,0)) -> 12 | L401: =E401*F401 -> 714.12 | M401: =IF(E401>=K401,L401*J401,0) -> 28.5648 | N401: =(L401-M401)*I401 -> 82.266624 | O401: =L401-M401+N401 -> 767.82182

Sheet Summary
A1: Sales Summary
A3: Revenue by Category
A4: Electronics | B4: =SUMIFS(Sales!$O:$O,Sales!$G:$G,A4) -> 281676.87
A5: Home & Kitchen | B5: =SUMIFS(Sales!$O:$O,Sales!$G:$G,A5) -> 131242.55
A6: Office Supplies | B6: =SUMIFS(Sales!$O:$O,Sales!$G:$G,A6) -> 750889.47
A7: Outdoor | B7: =SUMIFS(Sales!$O:$O,Sales!$G:$G,A7) -> 147316.38
A8: Apparel | B8: =SUMIFS(Sales!$O:$O,Sales!$G:$G,A8) -> 168454.79
A9: Total | B9: =SUM(B4:B8) -> 1479580.1
A11: Revenue by Region
A12: R01 | B12: =SUMIFS(Sales!$O:$O,Sales!$H:$H,A12) -> 177872.7
A13: R02 | B13: =SUMIFS(Sales!$O:$O,Sales!$H:$H,A13) -> 125560.74
A14: R03 | B14: =SUMIFS(Sales!$O:$O,Sales!$H:$H,A14) -> 117147.18
A15: R04 | B15: =SUMIFS(Sales!$O:$O,Sales!$H:$H,A15) -> 217589.36
A16: R05 | B16: =SUMIFS(Sales!$O:$O,Sales!$H:$H,A16) -> 176965.44
A17: R06 | B17: =SUMIFS(Sales!$O:$O,Sales!$H:$H,A17) -> 153348.49
A18: R07 | B18: =SUMIFS(Sales!$O:$O,Sales!$H:$H,A18) -> 210243.74
A19: R08 | B19: =SUMIFS(Sales!$O:$O,Sales!$H:$H,A19) -> 300852.4
A22: Average Product Margin | B22: =AVERAGE(ProductMargins) -> 0.39594167
A23: Average Regional Tax Rate | B23: =AVERAGE(TaxRateTable) -> 0.0896875
A25: Dynamic lookup -- pick a sheet:
A26: SelectedSheet | B26: Regions
A27: Row count of selected sheet | B27: =COUNTA(INDIRECT("'"&B26&"'!A:A"))-1 -> 8
